Metadata-Version: 1.0
Name: botovh
Version: 0.2.0
Summary: Is your domain name already taken? Tell BotOVH to grab it for you when it becomes available for registration.
Home-page: https://github.com/iamcryptoki/botovh
Author: Gael Gentil
Author-email: UNKNOWN
License: MIT
Keywords: api,bot,domain,names,ovh,payment,registrar,registration
Platform: UNKNOWN
